tools/__init__.py
tools/main.py
ctf_support_tools-0.0.1.dist-info/LICENSE
ctf_support_tools-0.0.1.dist-info/METADATA
ctf_support_tools-0.0.1.dist-info/WHEEL
ctf_support_tools-0.0.1.dist-info/top_level.txt
ctf_support_tools-0.0.1.dist-info/RECORD
