Metadata-Version: 2.1
Name: ctf-support-tools
Version: 0.0.1
Summary: CTF statistics collection package
Home-page: https://github.com/sergey-sobolev/ctf-tools
Author: Sergey Sobolev
Author-email: sergey.sobolev@outlook.com
Classifier: Programming Language :: Python :: 3.8
Classifier: License :: OSI Approved :: MIT License
Classifier: Operating System :: OS Independent
Requires-Python: >=3.6
License-File: LICENSE
Requires-Dist: requests (<=2.21.0)
